TaiwanLottery/__init__.py
TaiwanLottery/utils.py
tests/__init__.py
tests/test_lottery.py
tests/test_utils.py
taiwanlottery-1.5.1.dist-info/LICENSE
taiwanlottery-1.5.1.dist-info/METADATA
taiwanlottery-1.5.1.dist-info/WHEEL
taiwanlottery-1.5.1.dist-info/top_level.txt
taiwanlottery-1.5.1.dist-info/RECORD
