Metadata-Version: 2.1
Name: taiwanlottery
Version: 1.5.1
Summary: Taiwan Lottery Crawler 台灣彩券爬蟲
Author: Cliff Su
Author-email: stu01509@gmail.com
License: MIT
Project-URL: Source, https://github.com/stu01509/TaiwanLotteryCrawler
Keywords: python,taiwanlottery,crawler,lottery,taiwan,台灣彩券,樂透,彩券
Platform: unix
Platform: linux
Platform: osx
Platform: cygwin
Platform: win32
Classifier: Development Status :: 5 - Production/Stable
Classifier: Intended Audience :: Developers
Classifier: Programming Language :: Python :: 3
Classifier: Programming Language :: Python :: 3.6
Classifier: Programming Language :: Python :: 3.7
Classifier: Programming Language :: Python :: 3.8
Classifier: Programming Language :: Python :: 3.9
Classifier: Programming Language :: Python :: 3.10
Classifier: Operating System :: Unix
Classifier: Operating System :: MacOS :: MacOS X
Classifier: Operating System :: Microsoft :: Windows
Classifier: License :: OSI Approved :: MIT License
Classifier: Topic :: Internet :: WWW/HTTP
Classifier: Topic :: Software Development :: Libraries
Requires-Python: >=3.6
Provides-Extra: testing
License-File: LICENSE
